[
    {
        "fixedHeight": true,
        "font": "arial.ttf",
        "height": 14,
        "minWidth": 10,
        "name": "Label",
        "normal": {
            "textColor": {
                "a": 1.0,
                "b": 1.0,
                "g": 1.0,
                "r": 1.0
            }
        }
    },
    {
        "name": "Texture"
    },	
    {
        "active": {
            "textColor": {
                "a": 1.0,
                "b": 0.0,
                "g": 0.0,
                "r": 0.0
            },
            "texture": "ButtonActive.png"
        },
        "activeOn": {
            "textColor": {
                "a": 1.0,
                "b": 0.0,
                "g": 0.0,
                "r": 0.0
            },
            "texture": "ButtonActive.png"
        },
        "border": {
            "bottom": 4,
            "left": 2,
            "right": 2,
            "top": 2
        },
        "contentOffset": {
            "bottom": 0,
            "left": 3,
            "right": 3,
            "top": 2
        },
        "fixedHeight": true,
        "font": "arial.ttf",
        "height": 21,
        "hover": {
            "textColor": {
                "a": 1.0,
                "b": 0.699999988079071,
                "g": 0.699999988079071,
                "r": 0.699999988079071
            },
            "texture": "ButtonHover.png"
        },
        "hoverOn": {
            "textColor": {
                "a": 1.0,
                "b": 0.0,
                "g": 0.0,
                "r": 0.0
            },
            "texture": "ButtonActive.png"
        },
        "margins": {
            "bottom": 2,
            "left": 0,
            "right": 0,
            "top": 0
        },
        "minWidth": 20,
        "name": "Button",
        "normal": {
            "textColor": {
                "a": 1.0,
                "b": 0.699999988079071,
                "g": 0.699999988079071,
                "r": 0.699999988079071
            },
            "texture": "ButtonNormal.png"
        },
        "normalOn": {
            "textColor": {
                "a": 1.0,
                "b": 0.0,
                "g": 0.0,
                "r": 0.0
            },
            "texture": "ButtonActive.png"
        },
        "focused": {
            "textColor": {
                "a": 1.0,
                "b": 0.699999988079071,
                "g": 0.699999988079071,
                "r": 0.699999988079071
            },
            "texture": "ButtonFocused.png"
        },
        "focusedOn": {
            "textColor": {
                "a": 1.0,
                "b": 0.0,
                "g": 0.0,
                "r": 0.0
            },
            "texture": "ButtonFocused.png"
        },
        "focusedHover": {
            "textColor": {
                "a": 1.0,
                "b": 0.699999988079071,
                "g": 0.699999988079071,
                "r": 0.699999988079071
            },
            "texture": "ButtonFocusedHover.png"
        },
        "focusedHoverOn": {
            "textColor": {
                "a": 1.0,
                "b": 0.0,
                "g": 0.0,
                "r": 0.0
            },
            "texture": "ButtonFocusedHover.png"
        },
        "textHorzAlign": 1,
        "textVertAlign": 1
    },
    {
        "active": {
            "texture": "ToggleHover.png"
        },
        "activeOn": {
            "texture": "ToggleHoverOn.png"
        },
        "fixedHeight": true,
        "fixedWidth": true,
        "height": 15,
        "hover": {
            "texture": "ToggleHover.png"
        },
        "hoverOn": {
            "texture": "ToggleHoverOn.png"
        },
        "focusedHover": {
            "texture": "ToggleFocusedHover.png"
        },
        "focusedHoverOn": {
            "texture": "ToggleFocusedHoverOn.png"
        },
        "margins": {
            "bottom": 2,
            "left": 0,
            "right": 0,
            "top": 0
        },
        "name": "Toggle",
        "normal": {
            "texture": "ToggleNormal.png"
        },
        "normalOn": {
            "texture": "ToggleNormalOn.png"
        },
		"focused": {
            "texture": "ToggleFocused.png"
        },
        "focusedOn": {
            "texture": "ToggleFocusedOn.png"
        },
        "width": 13
    },
    {
        "active": {
            "textColor": {
                "a": 1.0,
                "b": 0.699999988079071,
                "g": 0.699999988079071,
                "r": 0.699999988079071
            },
            "texture": "InputBoxNormal.png"
        },
        "border": {
            "bottom": 1,
            "left": 1,
            "right": 3,
            "top": 4
        },
        "contentOffset": {
            "bottom": 4,
            "left": 4,
            "right": 4,
            "top": 4
        },
        "fixedHeight": true,
        "focused": {
            "textColor": {
                "a": 1.0,
                "b": 0.699999988079071,
                "g": 0.699999988079071,
                "r": 0.699999988079071
            },
            "texture": "InputBoxActive.png"
        },
        "font": "arial.ttf",
        "height": 19,
        "hover": {
            "textColor": {
                "a": 1.0,
                "b": 0.699999988079071,
                "g": 0.699999988079071,
                "r": 0.699999988079071
            },
            "texture": "InputBoxHover.png"
        },
        "minWidth": 10,
        "name": "InputBox",
        "normal": {
            "textColor": {
                "a": 1.0,
                "b": 0.699999988079071,
                "g": 0.699999988079071,
                "r": 0.699999988079071
            },
            "texture": "InputBoxNormal.png"
        }
    },
    {
        "active": {
            "texture": "ScrollArrowUpActive.png"
        },
        "fixedHeight": true,
        "fixedWidth": true,
        "height": 11,
        "hover": {
            "texture": "ScrollArrowUpHover.png"
        },
        "name": "ScrollUpBtn",
        "normal": {
            "texture": "ScrollArrowUpNormal.png"
        },
        "width": 13
    },
    {
        "active": {
            "texture": "ScrollArrowDownActive.png"
        },
        "fixedHeight": true,
        "fixedWidth": true,
        "height": 11,
        "hover": {
            "texture": "ScrollArrowDownHover.png"
        },
        "name": "ScrollDownBtn",
        "normal": {
            "texture": "ScrollArrowDownNormal.png"
        },
        "width": 13
    },
    {
        "active": {
            "texture": "ScrollArrowLeftActive.png"
        },
        "fixedHeight": true,
        "fixedWidth": true,
        "height": 13,
        "hover": {
            "texture": "ScrollArrowLeftHover.png"
        },
        "name": "ScrollLeftBtn",
        "normal": {
            "texture": "ScrollArrowLeftNormal.png"
        },
        "width": 11
    },
    {
        "active": {
            "texture": "ScrollArrowRightActive.png"
        },
        "fixedHeight": true,
        "fixedWidth": true,
        "height": 13,
        "hover": {
            "texture": "ScrollArrowRightHover.png"
        },
        "name": "ScrollRightBtn",
        "normal": {
            "texture": "ScrollArrowRightNormal.png"
        },
        "width": 11
    },
    {
        "active": {
            "texture": "ScrollBarHHandleActive.png"
        },
        "border": {
            "bottom": 0,
            "left": 4,
            "right": 4,
            "top": 0
        },
        "fixedHeight": true,
        "height": 13,
        "hover": {
            "texture": "ScrollBarHHandleHover.png"
        },
        "name": "ScrollBarHorzBtn",
        "normal": {
            "texture": "ScrollBarHHandleNormal.png"
        },
        "width": 10
    },
    {
        "active": {
            "texture": "ScrollBarVHandleActive.png"
        },
        "border": {
            "bottom": 4,
            "left": 0,
            "right": 0,
            "top": 4
        },
        "fixedWidth": true,
        "height": 10,
        "hover": {
            "texture": "ScrollBarVHandleHover.png"
        },
        "name": "ScrollBarVertBtn",
        "normal": {
            "texture": "ScrollBarVHandleNormal.png"
        },
        "width": 13
    },
    {
        "active": {
            "texture": "ScrollBarVBackground.png"
        },
        "fixedWidth": true,
        "hover": {
            "texture": "ScrollBarVBackground.png"
        },
        "minHeight": 8,
        "name": "ScrollBarVert",
        "normal": {
            "texture": "ScrollBarVBackground.png"
        },
        "subStyles": [
            {
                "name": "UIScrollBarHHandle",
                "style": "ScrollBarHorzBtn"
            },
            {
                "name": "UIScrollBarVHandle",
                "style": "ScrollBarVertBtn"
            }
        ],
        "width": 16
    },
    {
        "active": {
            "texture": "ScrollBarHBackground.png"
        },
        "fixedHeight": true,
        "height": 16,
        "hover": {
            "texture": "ScrollBarHBackground.png"
        },
        "minWidth": 8,
        "name": "ScrollBarHorz",
        "normal": {
            "texture": "ScrollBarHBackground.png"
        },
        "subStyles": [
            {
                "name": "UIScrollBarHHandle",
                "style": "ScrollBarHorzBtn"
            },
            {
                "name": "UIScrollBarVHandle",
                "style": "ScrollBarVertBtn"
            }
        ]
    },
    {
        "active": {
            "texture": "ScrollBarHHandleResizeableActive.png"
        },
        "border": {
            "bottom": 0,
            "left": 7,
            "right": 7,
            "top": 0
        },
        "fixedHeight": true,
        "height": 13,
        "hover": {
            "texture": "ScrollBarHHandleResizeableHover.png"
        },
        "minWidth": 15,
        "name": "ScrollBarResizeableHorzBtn",
        "normal": {
            "texture": "ScrollBarHHandleResizeableNormal.png"
        }
    },
    {
        "active": {
            "texture": "ScrollBarVHandleResizeableActive.png"
        },
        "border": {
            "bottom": 7,
            "left": 0,
            "right": 0,
            "top": 7
        },
        "fixedWidth": true,
        "hover": {
            "texture": "ScrollBarVHandleResizeableHover.png"
        },
        "minHeight": 15,
        "name": "ScrollBarResizeableVertBtn",
        "normal": {
            "texture": "ScrollBarVHandleResizeableNormal.png"
        },
        "width": 13
    },
    {
        "active": {
            "texture": "ScrollBarVBackground.png"
        },
        "fixedWidth": true,
        "hover": {
            "texture": "ScrollBarVBackground.png"
        },
        "minHeight": 15,
        "name": "ResizeableScrollBarVert",
        "normal": {
            "texture": "ScrollBarVBackground.png"
        },
        "subStyles": [
            {
                "name": "UIScrollBarHHandle",
                "style": "ScrollBarResizeableHorzBtn"
            },
            {
                "name": "UIScrollBarVHandle",
                "style": "ScrollBarResizeableVertBtn"
            }
        ],
        "width": 16
    },
    {
        "active": {
            "texture": "ScrollBarHBackground.png"
        },
        "fixedHeight": true,
        "height": 16,
        "hover": {
            "texture": "ScrollBarHBackground.png"
        },
        "minWidth": 15,
        "name": "ResizeableScrollBarHorz",
        "normal": {
            "texture": "ScrollBarHBackground.png"
        },
        "subStyles": [
            {
                "name": "UIScrollBarHHandle",
                "style": "ScrollBarResizeableHorzBtn"
            },
            {
                "name": "UIScrollBarVHandle",
                "style": "ScrollBarResizeableVertBtn"
            }
        ]
    },
    {
        "active": {
            "textColor": {
                "a": 1.0,
                "b": 0.699999988079071,
                "g": 0.699999988079071,
                "r": 0.699999988079071
            },
            "texture": "DropDownButtonActive.png"
        },
        "activeOn": {
            "textColor": {
                "a": 1.0,
                "b": 0.699999988079071,
                "g": 0.699999988079071,
                "r": 0.699999988079071
            },
            "texture": "DropDownButtonActive.png"
        },
        "border": {
            "bottom": 4,
            "left": 2,
            "right": 16,
            "top": 2
        },
        "contentOffset": {
            "bottom": 2,
            "left": 3,
            "right": 18,
            "top": 2
        },
        "fixedHeight": true,
        "font": "arial.ttf",
        "height": 21,
        "hover": {
            "textColor": {
                "a": 1.0,
                "b": 0.699999988079071,
                "g": 0.699999988079071,
                "r": 0.699999988079071
            },
            "texture": "DropDownButtonHover.png"
        },
        "hoverOn": {
            "textColor": {
                "a": 1.0,
                "b": 0.699999988079071,
                "g": 0.699999988079071,
                "r": 0.699999988079071
            },
            "texture": "DropDownButtonActive.png"
        },
		"focusedHover": {
            "textColor": {
                "a": 1.0,
                "b": 0.699999988079071,
                "g": 0.699999988079071,
                "r": 0.699999988079071
            },
            "texture": "DropDownButtonFocusedHover.png"
        },
        "focusedHoverOn": {
            "textColor": {
                "a": 1.0,
                "b": 0.699999988079071,
                "g": 0.699999988079071,
                "r": 0.699999988079071
            },
            "texture": "DropDownButtonFocusedHover.png"
        },
        "margins": {
            "bottom": 2,
            "left": 0,
            "right": 0,
            "top": 0
        },
        "minWidth": 20,
        "name": "ListBox",
        "normal": {
            "textColor": {
                "a": 1.0,
                "b": 0.699999988079071,
                "g": 0.699999988079071,
                "r": 0.699999988079071
            },
            "texture": "DropDownButtonNormal.png"
        },
        "normalOn": {
            "textColor": {
                "a": 1.0,
                "b": 0.699999988079071,
                "g": 0.699999988079071,
                "r": 0.699999988079071
            },
            "texture": "DropDownButtonActive.png"
        },
		"focused": {
            "textColor": {
                "a": 1.0,
                "b": 0.699999988079071,
                "g": 0.699999988079071,
                "r": 0.699999988079071
            },
            "texture": "DropDownButtonFocused.png"
        },
        "focusedOn": {
            "textColor": {
                "a": 1.0,
                "b": 0.699999988079071,
                "g": 0.699999988079071,
                "r": 0.699999988079071
            },
            "texture": "DropDownButtonFocused.png"
        },
        "textVertAlign": 1
    },
    {
        "active": {
            "texture": "DropDownBoxArrowUpHover.png"
        },
        "fixedHeight": true,
        "fixedWidth": true,
        "height": 12,
        "hover": {
            "texture": "DropDownBoxArrowUpHover.png"
        },
        "name": "ListBoxScrollUpBtn",
        "normal": {
            "texture": "DropDownBoxArrowUpNormal.png"
        },
        "width": 8
    },
    {
        "active": {
            "texture": "DropDownBoxArrowUpHover.png"
        },
        "fixedHeight": true,
        "fixedWidth": true,
        "height": 12,
        "hover": {
            "texture": "DropDownBoxArrowUpHover.png"
        },
        "name": "MenuBarScrollUpBtn",
        "normal": {
            "texture": "DropDownBoxArrowUpNormal.png"
        },
        "width": 8
    },
    {
        "active": {
            "texture": "DropDownBoxArrowUpHover.png"
        },
        "fixedHeight": true,
        "fixedWidth": true,
        "height": 12,
        "hover": {
            "texture": "DropDownBoxArrowUpHover.png"
        },
        "name": "ContextMenuScrollUpBtn",
        "normal": {
            "texture": "DropDownBoxArrowUpNormal.png"
        },
        "width": 8
    },
    {
        "active": {
            "texture": "DropDownBoxArrowDownHover.png"
        },
        "fixedHeight": true,
        "fixedWidth": true,
        "height": 12,
        "hover": {
            "texture": "DropDownBoxArrowDownHover.png"
        },
        "name": "ListBoxScrollDownBtn",
        "normal": {
            "texture": "DropDownBoxArrowDownNormal.png"
        },
        "width": 8
    },
    {
        "active": {
            "texture": "DropDownBoxArrowDownHover.png"
        },
        "fixedHeight": true,
        "fixedWidth": true,
        "height": 12,
        "hover": {
            "texture": "DropDownBoxArrowDownHover.png"
        },
        "name": "MenuBarScrollDownBtn",
        "normal": {
            "texture": "DropDownBoxArrowDownNormal.png"
        },
        "width": 8
    },
    {
        "active": {
            "texture": "DropDownBoxArrowDownHover.png"
        },
        "fixedHeight": true,
        "fixedWidth": true,
        "height": 12,
        "hover": {
            "texture": "DropDownBoxArrowDownHover.png"
        },
        "name": "ContextMenuScrollDownBtn",
        "normal": {
            "texture": "DropDownBoxArrowDownNormal.png"
        },
        "width": 8
    },
    {
        "fixedWidth": true,
        "height": 8,
        "name": "ListBoxHandle",
        "normal": {
            "texture": "DropDownBoxScrollHandle.png"
        },
        "width": 8
    },
    {
        "fixedWidth": true,
        "height": 8,
        "name": "MenuBarHandle",
        "normal": {
            "texture": "DropDownBoxScrollHandle.png"
        },
        "width": 8
    },
    {
        "fixedWidth": true,
        "height": 8,
        "name": "ContextMenuHandle",
        "normal": {
            "texture": "DropDownBoxScrollHandle.png"
        },
        "width": 8
    },
    {
        "border": {
            "bottom": 1,
            "left": 1,
            "right": 0,
            "top": 1
        },
        "fixedWidth": true,
        "height": 8,
        "name": "ListBoxSidebarBg",
        "normal": {
            "texture": "DropDownBoxSideBg.png"
        },
        "width": 9
    },
    {
        "border": {
            "bottom": 1,
            "left": 1,
            "right": 0,
            "top": 1
        },
        "fixedWidth": true,
        "height": 8,
        "name": "MenuBarSidebarBg",
        "normal": {
            "texture": "DropDownBoxSideBg.png"
        },
        "width": 9
    },
    {
        "border": {
            "bottom": 1,
            "left": 1,
            "right": 0,
            "top": 1
        },
        "fixedWidth": true,
        "height": 8,
        "name": "ContextMenuSidebarBg",
        "normal": {
            "texture": "DropDownBoxSideBg.png"
        },
        "width": 9
    },
    {
        "active": {
            "textColor": {
                "a": 1.0,
                "b": 0.699999988079071,
                "g": 0.699999988079071,
                "r": 0.699999988079071
            },
            "texture": "DropDownBoxEntryHover.png"
        },
        "activeOn": {
            "textColor": {
                "a": 1.0,
                "b": 0.699999988079071,
                "g": 0.699999988079071,
                "r": 0.699999988079071
            },
            "texture": "DropDownBoxEntryHover.png"
        },
        "fixedHeight": true,
        "font": "arial.ttf",
        "height": 16,
        "hover": {
            "textColor": {
                "a": 1.0,
                "b": 0.699999988079071,
                "g": 0.699999988079071,
                "r": 0.699999988079071
            },
            "texture": "DropDownBoxEntryHover.png"
        },
        "hoverOn": {
            "textColor": {
                "a": 1.0,
                "b": 0.699999988079071,
                "g": 0.699999988079071,
                "r": 0.699999988079071
            },
            "texture": "DropDownBoxEntryHover.png"
        },
        "name": "DropDownEntryBtn",
        "normal": {
            "textColor": {
                "a": 1.0,
                "b": 0.699999988079071,
                "g": 0.699999988079071,
                "r": 0.699999988079071
            },
            "texture": "DropDownBoxEntryNormal.png"
        },
        "normalOn": {
            "textColor": {
                "a": 1.0,
                "b": 0.699999988079071,
                "g": 0.699999988079071,
                "r": 0.699999988079071
            },
            "texture": "DropDownBoxEntryHover.png"
        },
        "textVertAlign": 1,
        "width": 30
    },
    {
        "active": {
            "textColor": {
                "a": 1.0,
                "b": 0.699999988079071,
                "g": 0.699999988079071,
                "r": 0.699999988079071
            },
            "texture": "DropDownBoxEntryToggleHover.png"
        },
        "activeOn": {
            "textColor": {
                "a": 1.0,
                "b": 0.699999988079071,
                "g": 0.699999988079071,
                "r": 0.699999988079071
            },
            "texture": "DropDownBoxEntryToggleHoverOn.png"
        },
        "border": {
            "bottom": 0,
            "left": 17,
            "right": 0,
            "top": 0
        },
        "contentOffset": {
            "bottom": 0,
            "left": 17,
            "right": 0,
            "top": 0
        },
        "fixedHeight": true,
        "font": "arial.ttf",
        "height": 18,
        "hover": {
            "textColor": {
                "a": 1.0,
                "b": 0.699999988079071,
                "g": 0.699999988079071,
                "r": 0.699999988079071
            },
            "texture": "DropDownBoxEntryToggleHover.png"
        },
        "hoverOn": {
            "textColor": {
                "a": 1.0,
                "b": 0.699999988079071,
                "g": 0.699999988079071,
                "r": 0.699999988079071
            },
            "texture": "DropDownBoxEntryToggleHoverOn.png"
        },
        "name": "DropDownEntryToggleBtn",
        "normal": {
            "textColor": {
                "a": 1.0,
                "b": 0.699999988079071,
                "g": 0.699999988079071,
                "r": 0.699999988079071
            },
            "texture": "DropDownBoxEntryToggleNormal.png"
        },
        "normalOn": {
            "textColor": {
                "a": 1.0,
                "b": 0.699999988079071,
                "g": 0.699999988079071,
                "r": 0.699999988079071
            },
            "texture": "DropDownBoxEntryToggleNormalOn.png"
        },
        "textVertAlign": 1,
        "width": 30
    },
    {
        "active": {
            "textColor": {
                "a": 1.0,
                "b": 0.699999988079071,
                "g": 0.699999988079071,
                "r": 0.699999988079071
            },
            "texture": "DropDownBoxExpandBtnHover.png"
        },
        "activeOn": {
            "textColor": {
                "a": 1.0,
                "b": 0.699999988079071,
                "g": 0.699999988079071,
                "r": 0.699999988079071
            },
            "texture": "DropDownBoxExpandBtnHover.png"
        },
        "border": {
            "bottom": 0,
            "left": 0,
            "right": 13,
            "top": 0
        },
        "fixedHeight": true,
        "font": "arial.ttf",
        "height": 16,
        "hover": {
            "textColor": {
                "a": 1.0,
                "b": 0.699999988079071,
                "g": 0.699999988079071,
                "r": 0.699999988079071
            },
            "texture": "DropDownBoxExpandBtnHover.png"
        },
        "hoverOn": {
            "textColor": {
                "a": 1.0,
                "b": 0.699999988079071,
                "g": 0.699999988079071,
                "r": 0.699999988079071
            },
            "texture": "DropDownBoxExpandBtnHover.png"
        },
        "name": "DropDownEntryExpBtn",
        "normal": {
            "textColor": {
                "a": 1.0,
                "b": 0.699999988079071,
                "g": 0.699999988079071,
                "r": 0.699999988079071
            },
            "texture": "DropDownBoxExpandBtnNormal.png"
        },
        "normalOn": {
            "textColor": {
                "a": 1.0,
                "b": 0.699999988079071,
                "g": 0.699999988079071,
                "r": 0.699999988079071
            },
            "texture": "DropDownBoxExpandBtnHover.png"
        },
        "textVertAlign": 1,
        "width": 30
    },
    {
        "fixedHeight": true,
        "height": 3,
        "name": "DropDownSeparator",
        "normal": {
            "texture": "DropDownBoxSeparator.png"
        },
        "width": 30
    },
    {
        "minHeight": 20,
        "minWidth": 50,
        "name": "ListBoxContent",
        "subStyles": [
            {
                "name": "DropDownEntryBtn",
                "style": "DropDownEntryBtn"
            },
            {
                "name": "DropDownEntryExpBtn",
                "style": "DropDownEntryExpBtn"
            },
            {
                "name": "DropDownEntryToggleBtn",
                "style": "DropDownEntryToggleBtn"
            },
            {
                "name": "DropDownSeparator",
                "style": "DropDownSeparator"
            }
        ]
    },
    {
        "minHeight": 20,
        "minWidth": 50,
        "name": "MenuBarContent",
        "subStyles": [
            {
                "name": "DropDownEntryBtn",
                "style": "DropDownEntryBtn"
            },
            {
                "name": "DropDownEntryExpBtn",
                "style": "DropDownEntryExpBtn"
            },
            {
                "name": "DropDownEntryToggleBtn",
                "style": "DropDownEntryToggleBtn"
            },
            {
                "name": "DropDownSeparator",
                "style": "DropDownSeparator"
            }
        ]
    },
    {
        "minHeight": 20,
        "minWidth": 50,
        "name": "ContextMenuContent",
        "subStyles": [
            {
                "name": "DropDownEntryBtn",
                "style": "DropDownEntryBtn"
            },
            {
                "name": "DropDownEntryExpBtn",
                "style": "DropDownEntryExpBtn"
            },
            {
                "name": "DropDownEntryToggleBtn",
                "style": "DropDownEntryToggleBtn"
            },
            {
                "name": "DropDownSeparator",
                "style": "DropDownSeparator"
            }
        ]
    },
    {
        "active": {
            "texture": "DropDownBoxBg.png"
        },
        "border": {
            "bottom": 4,
            "left": 2,
            "right": 2,
            "top": 2
        },
        "hover": {
            "texture": "DropDownBoxBg.png"
        },
        "margins": {
            "bottom": 6,
            "left": 6,
            "right": 6,
            "top": 4
        },
        "name": "ListBoxFrame",
        "normal": {
            "texture": "DropDownBoxBg.png"
        }
    },
    {
        "active": {
            "texture": "DropDownBoxBg.png"
        },
        "border": {
            "bottom": 4,
            "left": 2,
            "right": 2,
            "top": 2
        },
        "hover": {
            "texture": "DropDownBoxBg.png"
        },
        "margins": {
            "bottom": 6,
            "left": 6,
            "right": 6,
            "top": 4
        },
        "name": "MenuBarFrame",
        "normal": {
            "texture": "DropDownBoxBg.png"
        }
    },
    {
        "active": {
            "texture": "DropDownBoxBg.png"
        },
        "border": {
            "bottom": 4,
            "left": 2,
            "right": 2,
            "top": 2
        },
        "hover": {
            "texture": "DropDownBoxBg.png"
        },
        "margins": {
            "bottom": 6,
            "left": 6,
            "right": 6,
            "top": 4
        },
        "name": "ContextMenuFrame",
        "normal": {
            "texture": "DropDownBoxBg.png"
        }
    },
    {
        "active": {
            "texture": "DropDownBoxBg.png"
        },
        "border": {
            "bottom": 4,
            "left": 2,
            "right": 2,
            "top": 2
        },
        "hover": {
            "texture": "DropDownBoxBg.png"
        },
        "margins": {
            "bottom": 6,
            "left": 6,
            "right": 6,
            "top": 4
        },
        "name": "TooltipFrame",
        "normal": {
            "texture": "DropDownBoxBg.png"
        }
    },
    {
        "active": {
            "texture": "SliderHandleActive.png"
        },
        "fixedHeight": true,
        "fixedWidth": true,
        "height": 13,
        "hover": {
            "texture": "SliderHandleHover.png"
        },
        "name": "SliderHandle",
        "normal": {
            "texture": "SliderHandleNormal.png"
        },
        "width": 12
    },
    {
        "border": {
            "bottom": 0,
            "left": 4,
            "right": 4,
            "top": 0
        },
        "fixedHeight": true,
        "height": 10,
        "name": "SliderHorzBg",
        "normal": {
            "texture": "SliderHBackground.png"
        },
		"focused": {
            "texture": "SliderHBackgroundFocused.png"
        }
    },
    {
        "border": {
            "bottom": 0,
            "left": 6,
            "right": 4,
            "top": 0
        },
        "fixedHeight": true,
        "height": 10,
        "name": "SliderHorzFill",
        "normal": {
            "texture": "SliderHFill.png"
        }
    },
    {
        "fixedHeight": true,
        "height": 13,
        "minWidth": 10,
        "name": "SliderHorz",
        "subStyles": [
            {
                "name": "SliderBackground",
                "style": "SliderHorzBg"
            },
            {
                "name": "SliderFill",
                "style": "SliderHorzFill"
            },
            {
                "name": "SliderHandle",
                "style": "SliderHandle"
            }
        ],
        "width": 150
    },
    {
        "border": {
            "bottom": 4,
            "left": 0,
            "right": 0,
            "top": 4
        },
        "fixedWidth": true,
        "name": "SliderVertBg",
        "normal": {
            "texture": "SliderVBackground.png"
        },
		"focused": {
            "texture": "SliderVBackgroundFocused.png"
        },
        "width": 10
    },
    {
        "border": {
            "bottom": 4,
            "left": 0,
            "right": 0,
            "top": 6
        },
        "fixedWidth": true,
        "name": "SliderVertFill",
        "normal": {
            "texture": "SliderVFill.png"
        },
        "width": 10
    },
    {
        "fixedWidth": true,
        "height": 150,
        "minHeight": 10,
        "name": "SliderVert",
        "subStyles": [
            {
                "name": "SliderBackground",
                "style": "SliderVertBg"
            },
            {
                "name": "SliderFill",
                "style": "SliderVertFill"
            },
            {
                "name": "SliderHandle",
                "style": "SliderHandle"
            }
        ],
        "width": 13
    },
    {
        "fixedHeight": true,
        "font": "arial.ttf",
        "height": 11,
        "minWidth": 10,
        "name": "RightAlignedLabel",
        "normal": {
            "textColor": {
                "a": 1.0,
                "b": 0.699999988079071,
                "g": 0.699999988079071,
                "r": 0.699999988079071
            }
        },
        "textHorzAlign": 2
    }
]
